git_api/__init__.py
git_api/main.py
git_api-1.7.5.dist-info/LICENSE
git_api-1.7.5.dist-info/METADATA
git_api-1.7.5.dist-info/WHEEL
git_api-1.7.5.dist-info/top_level.txt
git_api-1.7.5.dist-info/zip-safe
git_api-1.7.5.dist-info/RECORD
