Metadata-Version: 2.1
Name: git-api
Version: 1.7.5
Summary: A GitHub API. Extracts data from GitHub into json style data.
Home-page: https://github.com/JBYT27/Git-API
Author: JBYT27
Author-email: beol0127@gmail.com
License: MIT
Platform: UNKNOWN
Classifier: Programming Language :: Python :: 3
Classifier: License :: OSI Approved :: MIT License
Classifier: Operating System :: OS Independent
Requires-Python: >=3.6
License-File: LICENSE
